foram/__init__.py
tests/__init__.py
tests/test_metadata.py
foram-0.0.1.dist-info/LICENSE
foram-0.0.1.dist-info/METADATA
foram-0.0.1.dist-info/WHEEL
foram-0.0.1.dist-info/top_level.txt
foram-0.0.1.dist-info/RECORD
